[
  {
    "term": "music/%2801%29%20%5BDionysis%20Savvopoulos%5D%20Fifteen%20guys%20%28I%20dekapente%29.mp3",
    "definition": "Dionysis Savvopoulos - Fifteen guys (I dekapente)",
    "emoji": "🎭"
  },
  {
    "term": "music/%2802%29%20%5BDionysis%20Savvopoulos%5D%20The%20barrack%20%28I%20paragka%29.mp3",
    "definition": "Dionysis Savvopoulos - The barrack (I paragka)",
    "emoji": "🎉"
  },
  {
    "term": "music/%2803%29%20%5BDionysis%20Savvopoulos%5D%20The%20barrack%20%28I%20paragka%29%20%5BWith%20guitar%5D.mp3",
    "definition": "Dionysis Savvopoulos - The barrack (I paragka) [With guitar]",
    "emoji": "🎹"
  },
  {
    "term": "music/%2804%29%20%5BDionysis%20Savvopoulos%5D%20The%20beast%20%28To%20thirio%29.mp3",
    "definition": "Dionysis Savvopoulos - The beast (To thirio)",
    "emoji": "🏆"
  },
  {
    "term": "music/%2805%29%20%5BDionysis%20Savvopoulos%5D%20Physical%20need%20%28Somatiki%20anagki%29.mp3",
    "definition": "Dionysis Savvopoulos - Physical need (Somatiki anagki)",
    "emoji": "🎨"
  },
  {
    "term": "music/%2806%29%20%5BDionysis%20Savvopoulos%5D%20A%20small%20sea%20%28Mia%20thalasa%20mikri%29.mp3",
    "definition": "Dionysis Savvopoulos - A small sea (Mia thalasa mikri)",
    "emoji": "💯"
  },
  {
    "term": "music/%2807%29%20%5BDionysis%20Savvopoulos%5D%20At%20the%20gathering%20%28Sti%20sigkentrosi%29.mp3",
    "definition": "Dionysis Savvopoulos - At the gathering (Sti sigkentrosi)",
    "emoji": "💃"
  },
  {
    "term": "music/%2808%29%20%5BDionysis%20Savvopoulos%5D%20I%20don%27t%20need%20your%20songs%20%28Ti%20na%20ta%20kano%20ta%20tragoudia%20sas%29.mp3",
    "definition": "Dionysis Savvopoulos - I don't need your songs (Ti na ta kano ta tragoudia sas)",
    "emoji": "🌸"
  },
  {
    "term": "music/%2809%29%20%5BDionysis%20Savvopoulos%5D%20Test%20%28Dokimi%29.mp3",
    "definition": "Dionysis Savvopoulos - Test (Dokimi)",
    "emoji": "⭐"
  },
  {
    "term": "music/%2810%29%20%5BDionysis%20Savvopoulos%5D%20Note%20%28Simioma%29.mp3",
    "definition": "Dionysis Savvopoulos - Note (Simioma)",
    "emoji": "🤘"
  },
  {
    "term": "music/%2811%29%20%5BDionysis%20Savvopoulos%5D%20The%20mortal%20solitude%20of%20Alexis%20Aslanis%20%28I%20thanasimi%20monaxia%20tou%20Alexi%20Aslani%29.mp3",
    "definition": "Dionysis Savvopoulos - The mortal solitude of Alexis Aslanis (I thanasimi monaxia tou Alexi Aslani)",
    "emoji": "🎭"
  },
  {
    "term": "music/%2812%29%20%5BDionysis%20Savvopoulos%5D%20Aunt%20Manou%20%28I%20thia%20Manou%29.mp3",
    "definition": "Dionysis Savvopoulos - Aunt Manou (I thia Manou)",
    "emoji": "🏆"
  },
  {
    "term": "music/%2813%29%20%5BDionysis%20Savvopoulos%5D%20Wire%20%28Sirma%29.mp3",
    "definition": "Dionysis Savvopoulos - Wire (Sirma)",
    "emoji": "🎉"
  },
  {
    "term": "music/%2814%29%20%5BDionysis%20Savvopoulos%5D%20Olaria%20olara.mp3",
    "definition": "Dionysis Savvopoulos - Olaria olara",
    "emoji": "🐝"
  },
  {
    "term": "music/%2815%29%20%5BDionysis%20Savvopoulos%5D%20Zeimbekiko.mp3",
    "definition": "Dionysis Savvopoulos - Zeimbekiko",
    "emoji": "🌙"
  },
  {
    "term": "music/%2816%29%20%5BDionysis%20Savvopoulos%5D%20Like%20Karagkiozis%20%28Sna%20ton%20Karagkiozi%29.mp3",
    "definition": "Dionysis Savvopoulos - Like Karagkiozis (Sna ton Karagkiozi)",
    "emoji": "✨"
  },
  {
    "term": "music/%2817%29%20%5BDionysis%20Savvopoulos%5D%20Anniversary%20%28Epetios%29.mp3",
    "definition": "Dionysis Savvopoulos - Anniversary (Epetios)",
    "emoji": "🎺"
  }
]